CHANGELOG.txt
LICENCE.txt
MANIFEST.in
README.txt
setup.py
dpye/__init__.py
dpye.egg-info/PKG-INFO
dpye.egg-info/SOURCES.txt
dpye.egg-info/dependency_links.txt
dpye.egg-info/top_level.txt