Metadata-Version: 1.1
Name: dpye
Version: 0.0.2
Summary: discord.py-easy
Home-page: UNKNOWN
Author: 𝘼𝙦𝙪𝙖 𝙠𝙪𝙣 ⚚
Author-email: sasha136125429@gmail.com
License: MIT
Keywords: discord,discord.py,easy,discord.py-easy
Platform: UNKNOWN
Classifier: Development Status :: 5 - Production/Stable
Classifier: Intended Audience :: Education
Classifier: Operating System :: Microsoft :: Windows :: Windows 10
Classifier: License :: OSI Approved :: MIT License
Classifier: Programming Language :: Python :: 3
